dev/__init__.py
dev/lats_18.py
dev/lats_19.py
dev/lats_38dev.py
dev/pre_process_17.py
pylats/10k_pos_noes.pickle
pylats/10k_raw_noes.pickle
pylats/__init__.py
pylats/cedel_ignore.pickle
pylats/corp_raw_freq_escow_ax01_2021-04-28_5.json
pylats/lats.py
pylats/real_words5.pickle
pylats-0.39.dist-info/METADATA
pylats-0.39.dist-info/WHEEL
pylats-0.39.dist-info/top_level.txt
pylats-0.39.dist-info/RECORD
