Metadata-Version: 2.4
Name: pylats
Version: 0.39
Summary: Text preprocessing for downstream linguistic analyses
Home-page: https://github.com/LCR-ADS-Lab/pylats
Author: Kristopher Kyle
Author-email: kristopherkyle1@gmail.com
Classifier: Programming Language :: Python :: 3
Classifier: Operating System :: OS Independent
Dynamic: author
Dynamic: author-email
Dynamic: classifier
Dynamic: description
Dynamic: description-content-type
Dynamic: home-page
Dynamic: summary
